CMakeLists.txt
MANIFEST.in
README.md
pyproject.toml
setup.py
csrc/CMakeLists.txt
csrc/bindings.cpp
csrc/build/CMakeCache.txt
csrc/build/CMakeFiles/CMakeConfigureLog.yaml
csrc/build/CMakeFiles/cmake.check_cache
csrc/build/CMakeFiles/4.2.1/CMakeCCompiler.cmake
csrc/build/CMakeFiles/4.2.1/CMakeCXXCompiler.cmake
csrc/build/CMakeFiles/4.2.1/CMakeDetermineCompilerABI_C.bin
csrc/build/CMakeFiles/4.2.1/CMakeDetermineCompilerABI_CXX.bin
csrc/build/CMakeFiles/4.2.1/CMakeSystem.cmake
csrc/build/CMakeFiles/4.2.1/CompilerIdC/CMakeCCompilerId.c
csrc/build/CMakeFiles/4.2.1/CompilerIdC/a.out
csrc/build/CMakeFiles/4.2.1/CompilerIdCXX/CMakeCXXCompilerId.cpp
csrc/build/CMakeFiles/4.2.1/CompilerIdCXX/a.out
csrc/include/adjoint_diff.h
csrc/include/handle_manager.h
csrc/include/state_vector.h
csrc/src/adjoint_diff.cu
csrc/src/handle_manager.cu
csrc/src/state_vector.cu
tests/test_circuit.py
tests/test_cpp_backend.py
tests/test_gates.py
tests/test_gradients.py
torchqml/__init__.py
torchqml/autograd.py
torchqml/backend.py
torchqml/circuit.py
torchqml/functional.py
torchqml/gates.py
torchqml/nn.py
torchqml/operators.py
torchqml.egg-info/PKG-INFO
torchqml.egg-info/SOURCES.txt
torchqml.egg-info/dependency_links.txt
torchqml.egg-info/requires.txt
torchqml.egg-info/top_level.txt