Metadata-Version: 2.4
Name: torchqml
Version: 0.1.7
Summary: PyTorch Quantum Machine Learning with cuQuantum - Fast Adjoint Differentiation
Author: Your Name
Author-email: Masaki Shiraishi <masaki.shiraishi@fuji.waseda.jp>
License: MIT
Project-URL: Homepage, https://github.com/masa-whitestone/torch-qml
Project-URL: Bug Reports, https://github.com/masa-whitestone/torch-qml/issues
Project-URL: Source, https://github.com/masa-whitestone/torch-qml
Keywords: quantum,machine learning,pytorch,cuquantum,adjoint differentiation
Classifier: Development Status :: 3 - Alpha
Classifier: Intended Audience :: Science/Research
Classifier: License :: OSI Approved :: MIT License
Classifier: Programming Language :: Python :: 3
Classifier: Programming Language :: Python :: 3.8
Classifier: Programming Language :: Python :: 3.9
Classifier: Programming Language :: Python :: 3.10
Classifier: Programming Language :: Python :: 3.11
Classifier: Topic :: Scientific/Engineering :: Physics
Classifier: Topic :: Scientific/Engineering :: Artificial Intelligence
Requires-Python: >=3.8
Requires-Dist: torch>=2.0.0
Requires-Dist: numpy>=1.20.0
Requires-Dist: cupy-cuda12x>=12.0.0
Requires-Dist: cuquantum-python-cu12
Provides-Extra: dev
Requires-Dist: pytest>=7.0.0; extra == "dev"
Requires-Dist: pytest-cov>=4.0.0; extra == "dev"
Requires-Dist: black>=23.0.0; extra == "dev"
Requires-Dist: isort>=5.12.0; extra == "dev"
Requires-Dist: mypy>=1.0.0; extra == "dev"
Provides-Extra: benchmark
Requires-Dist: pennylane>=0.30.0; extra == "benchmark"
Requires-Dist: pennylane-lightning[gpu]>=0.30.0; extra == "benchmark"
Dynamic: author
Dynamic: requires-python
